thingpin/__init__.py
thingpin/__init__.pyc
thingpin/logger.py
thingpin/logger.pyc
thingpin/main.py
thingpin/main.pyc
thingpin/notifiers.py
thingpin/notifiers.pyc
thingpin/pin.py
thingpin/pin.pyc
thingpin/thingpin-config.yml.sample
thingpin/thingpin.py
thingpin/thingpin.pyc
thingpin-3.0.2.dist-info/DESCRIPTION.rst
thingpin-3.0.2.dist-info/METADATA
thingpin-3.0.2.dist-info/RECORD
thingpin-3.0.2.dist-info/WHEEL
thingpin-3.0.2.dist-info/entry_points.txt
thingpin-3.0.2.dist-info/metadata.json
thingpin-3.0.2.dist-info/pbr.json
thingpin-3.0.2.dist-info/top_level.txt
