Metadata-Version: 2.0
Name: thingpin
Version: 3.0.2
Summary: Raspberry Pi pin monitor that reports to AWS IoT
Home-page: https://github.com/mgk/thingpin/blob/master/README.md
Author: Michael Keirnan
Author-email: michael@keirnan.com
License: MIT
Keywords: aws iot thing mqtt sensor gpio raspberry pi rpi
Platform: any
Classifier: Development Status :: 4 - Beta
Classifier: Intended Audience :: Developers
Classifier: Intended Audience :: Science/Research
Classifier: Environment :: Console
Classifier: License :: OSI Approved :: MIT License
Classifier: Natural Language :: English
Classifier: Topic :: Home Automation
Classifier: Topic :: Internet
Classifier: Topic :: Software Development :: Libraries :: Python Modules
Classifier: Topic :: Scientific/Engineering
Classifier: Programming Language :: Python
Classifier: Programming Language :: Python :: 2
Classifier: Programming Language :: Python :: 2.7
Requires-Dist: docopt
Requires-Dist: python-daemon
Requires-Dist: pyyaml
Requires-Dist: thingamon (>=0.2.2)
